[{"model": "app.giftcardrate", "pk": 1, "fields": {"giftcard": 5, "currency": 1, "card_type": 1, "denomination": 1, "rate": "1230"}}, {"model": "app.giftcardrate", "pk": 2, "fields": {"giftcard": 5, "currency": 1, "card_type": 2, "denomination": 1, "rate": "2000"}}, {"model": "app.giftcardrate", "pk": 3, "fields": {"giftcard": 5, "currency": 2, "card_type": 1, "denomination": 1, "rate": "1400"}}, {"model": "app.giftcardrate", "pk": 4, "fields": {"giftcard": 5, "currency": 2, "card_type": 2, "denomination": 1, "rate": "1600"}}, {"model": "app.giftcardrate", "pk": 5, "fields": {"giftcard": 5, "currency": 3, "card_type": 1, "denomination": 1, "rate": "1370"}}, {"model": "app.giftcardrate", "pk": 6, "fields": {"giftcard": 5, "currency": 3, "card_type": 2, "denomination": 1, "rate": "1781"}}, {"model": "app.giftcardrate", "pk": 7, "fields": {"giftcard": 1, "currency": 4, "card_type": 7, "denomination": 4, "rate": "1200"}}, {"model": "app.giftcardrate", "pk": 8, "fields": {"giftcard": 7, "currency": 9, "card_type": 11, "denomination": 6, "rate": "2130"}}, {"model": "app.giftcardrate", "pk": 9, "fields": {"giftcard": 4, "currency": 8, "card_type": 9, "denomination": 2, "rate": "1670"}}, {"model": "app.giftcardrate", "pk": 10, "fields": {"giftcard": 8, "currency": 10, "card_type": 12, "denomination": 7, "rate": "1230"}}, {"model": "app.giftcardrate", "pk": 11, "fields": {"giftcard": 9, "currency": 14, "card_type": 1, "denomination": 8, "rate": "1000"}}, {"model": "app.giftcardrate", "pk": 12, "fields": {"giftcard": 9, "currency": 14, "card_type": 13, "denomination": 8, "rate": "1000"}}, {"model": "app.giftcardrate", "pk": 13, "fields": {"giftcard": 9, "currency": 14, "card_type": 13, "denomination": 17, "rate": "900"}}, {"model": "app.giftcardrate", "pk": 14, "fields": {"giftcard": 9, "currency": 14, "card_type": 14, "denomination": 17, "rate": "900"}}, {"model": "app.giftcardrate", "pk": 15, "fields": {"giftcard": 9, "currency": 15, "card_type": 14, "denomination": 8, "rate": "1000"}}, {"model": "app.giftcardrate", "pk": 16, "fields": {"giftcard": 9, "currency": 15, "card_type": 14, "denomination": 17, "rate": "900"}}, {"model": "app.giftcardrate", "pk": 17, "fields": {"giftcard": 13, "currency": 20, "card_type": 21, "denomination": 19, "rate": "800"}}, {"model": "app.giftcardrate", "pk": 18, "fields": {"giftcard": 13, "currency": 34, "card_type": 21, "denomination": 19, "rate": "900"}}, {"model": "app.giftcardrate", "pk": 19, "fields": {"giftcard": 13, "currency": 20, "card_type": 10, "denomination": 19, "rate": "950"}}, {"model": "app.giftcardrate", "pk": 20, "fields": {"giftcard": 13, "currency": 34, "card_type": 10, "denomination": 19, "rate": "980"}}, {"model": "app.giftcardrate", "pk": 21, "fields": {"giftcard": 13, "currency": 20, "card_type": 21, "denomination": 30, "rate": "980"}}, {"model": "app.giftcardrate", "pk": 22, "fields": {"giftcard": 13, "currency": 34, "card_type": 10, "denomination": 30, "rate": "1070"}}]